{
    "type": "FeatureCollection",
    "features": [
        {
            "type": "Feature",
            "properties": {},
            "geometry": {
                "type": "LineString",
                "coordinates": [
                    [
                        112.93407797813414,
                        28.154024912363496
                    ],
                    [
                        112.93409943580626,
                        28.154128965992335
                    ],
                    [
                        112.93419599533081,
                        28.154223560112584
                    ],
                    [
                        112.93427109718323,
                        28.154280316544636
                    ],
                    [
                        112.9383373260498,
                        28.154157344237188
                    ],
                    [
                        112.93832659721375,
                        28.152965451476785
                    ]
                ]
            }
        }
    ]
}